{
  "version": "v3_focal_loss",
  "description": "v2 + Focal Loss (gamma=2.0) cho head plaque",
  "summary": {
    "sensitivity": {
      "mean": 0.6632,
      "std": 0.1181
    },
    "specificity": {
      "mean": 0.761,
      "std": 0.153
    },
    "f1": {
      "mean": 0.6125,
      "std": 0.0405
    },
    "auc_roc": {
      "mean": 0.7358,
      "std": 0.0364
    },
    "pr_auc": {
      "mean": 0.6688,
      "std": 0.0353
    },
    "best_threshold": {
      "mean": 0.5518,
      "std": 0.0435
    },
    "macro_f1": {
      "mean": 0.6583,
      "std": 0.3781
    },
    "mae": {
      "mean": 0.5087,
      "std": 0.0648
    },
    "r2": {
      "mean": -0.0192,
      "std": 0.109
    },
    "val_loss": {
      "mean": 1.5899,
      "std": 1.687
    }
  },
  "fold_results": [
    {
      "sensitivity": 0.8421,
      "specificity": 0.5366,
      "f1": 0.5926,
      "auc_roc": 0.7458,
      "pr_auc": 0.6434,
      "best_threshold": 0.5121,
      "macro_f1": 0.1975,
      "mae": 0.4587,
      "r2": -0.0686,
      "val_loss": 4.6585
    },
    {
      "sensitivity": 0.6842,
      "specificity": 0.7561,
      "f1": 0.619,
      "auc_roc": 0.7715,
      "pr_auc": 0.7119,
      "best_threshold": 0.4966,
      "macro_f1": 1.0,
      "mae": 0.4919,
      "r2": -0.0242,
      "val_loss": 0.3035
    },
    {
      "sensitivity": 0.6316,
      "specificity": 0.9024,
      "f1": 0.6857,
      "auc_roc": 0.7651,
      "pr_auc": 0.6908,
      "best_threshold": 0.587,
      "macro_f1": 0.1975,
      "mae": 0.5975,
      "r2": -0.0529,
      "val_loss": 2.1744
    },
    {
      "sensitivity": 0.6842,
      "specificity": 0.6585,
      "f1": 0.5652,
      "auc_roc": 0.6701,
      "pr_auc": 0.6138,
      "best_threshold": 0.5517,
      "macro_f1": 0.8963,
      "mae": 0.5685,
      "r2": -0.1362,
      "val_loss": 0.4968
    },
    {
      "sensitivity": 0.4737,
      "specificity": 0.9512,
      "f1": 0.6,
      "auc_roc": 0.7266,
      "pr_auc": 0.6841,
      "best_threshold": 0.6117,
      "macro_f1": 1.0,
      "mae": 0.4267,
      "r2": 0.186,
      "val_loss": 0.3162
    }
  ]
}